{
  "parent": "disenchanter:recipes/root",
  "rewards": {
    "recipes": [
      "disenchanter:upgrade_jar_overload"
    ]
  },
  "criteria": {
    "has_the_recipe": {
      "trigger": "minecraft:recipe_unlocked",
      "conditions": {
        "recipe": "disenchanter:upgrade_jar_overload"
      }
    },
    "has_experience_jar": {
      "trigger": "minecraft:inventory_changed",
      "conditions": {
        "items": [{
          "item": "disenchanter:experience_jar"
        }]
      }
    }
  },
  "conditions": [{
    "type": "disenchanter:overload_upgrade_enabled"
  }],
  "requirements": [
    [
      "has_the_recipe",
      "has_experience_jar"
    ]
  ]
}
